theisle/Player.py
theisle/Server.py
theisle/__init__.py
theisle-0.0.1.dist-info/LICENSE
theisle-0.0.1.dist-info/METADATA
theisle-0.0.1.dist-info/WHEEL
theisle-0.0.1.dist-info/top_level.txt
theisle-0.0.1.dist-info/RECORD
